wwinpy/__init__.py
wwinpy/_config.py
wwinpy/_exceptions.py
wwinpy/_ratios.py
wwinpy/_utils.py
wwinpy/geometry.py
wwinpy/header.py
wwinpy/mesh.py
wwinpy/parser.py
wwinpy/plotter.py
wwinpy/query.py
wwinpy/weight_windows.py
wwinpy/ww_data.py
wwinpy-0.1.11.dist-info/LICENSE
wwinpy-0.1.11.dist-info/METADATA
wwinpy-0.1.11.dist-info/WHEEL
wwinpy-0.1.11.dist-info/RECORD
