Metadata-Version: 2.1
Name: wwinpy
Version: 0.1.11
Summary: Python library to parse and work with weight window files
Home-page: https://github.com/monleon96/WWINPy.git
License: GNU General Public License v3.0
Author: Juan Antonio Monleon de la Lluvia
Author-email: juanmonleon96@gmail.com
Requires-Python: >=3.12,<4.0
Classifier: License :: Other/Proprietary License
Classifier: Programming Language :: Python :: 3
Classifier: Programming Language :: Python :: 3.12
Classifier: Programming Language :: Python :: 3.13
Provides-Extra: docs
Requires-Dist: nbformat (>=5.10.4,<6.0.0)
Requires-Dist: numba (>=0.60.0,<0.61.0)
Requires-Dist: pandas (>=2.2.3,<3.0.0)
Requires-Dist: plotly (>=5.24.1,<6.0.0)
Requires-Dist: pyvista (>=0.44.2,<0.45.0)
